transcribe_diarize_emote/__init__.py
transcribe_diarize_emote/diarization.py
transcribe_diarize_emote/emotion.py
transcribe_diarize_emote/emotion_alignment.py
transcribe_diarize_emote/intermediate_vtt.py
transcribe_diarize_emote/models.py
transcribe_diarize_emote/pipeline.py
transcribe_diarize_emote/transcription.py
transcribe_diarize_emote/formatting/json_formatter.py
transcribe_diarize_emote/formatting/text_formatter.py
transcribe_diarize_emote/formatting/vtt_formatter.py
transcribe_diarize_emote-0.1.2.dist-info/licenses/LICENSE
transcribe_diarize_emote-0.1.2.dist-info/METADATA
transcribe_diarize_emote-0.1.2.dist-info/WHEEL
transcribe_diarize_emote-0.1.2.dist-info/top_level.txt
transcribe_diarize_emote-0.1.2.dist-info/RECORD
