Metadata-Version: 2.4
Name: transcribe-diarize-emote
Version: 0.1.2
Summary: End-to-end audio pipeline: transcription + diarization + emotion enrichment
Author: Ashwin B
License-Expression: MIT
Project-URL: Homepage, https://github.com/ashley1902/transcribe-diarize-emote
Project-URL: Repository, https://github.com/ashley1902/transcribe-diarize-emote
Project-URL: Issues, https://github.com/ashley1902/transcribe-diarize-emote/issues
Requires-Python: >=3.9
License-File: LICENSE
Requires-Dist: faster-whisper
Requires-Dist: diarizer-lite>=0.1.0
Requires-Dist: whisper-speaker-emotion>=0.1.0
Requires-Dist: numpy
Requires-Dist: scipy
Requires-Dist: librosa
Requires-Dist: soundfile
Requires-Dist: tqdm
Dynamic: license-file
